vyxm/__init__.py
vyxm/protocol/RegistryVisualizer.py
vyxm/protocol/__init__.py
vyxm/protocol/agent_specialists.py
vyxm/protocol/core.py
vyxm/protocol/distributor.py
vyxm/protocol/planner.py
vyxm/protocol/prebuilt_tools.py
vyxm/protocol/registry.py
vyxm/protocol/specialists.py
vyxm/protocol/tools.py
vyxm-0.0.8.dist-info/licenses/LICENSE
vyxm-0.0.8.dist-info/METADATA
vyxm-0.0.8.dist-info/WHEEL
vyxm-0.0.8.dist-info/top_level.txt
vyxm-0.0.8.dist-info/RECORD
